repo_fetcher/__init__.py
repo_fetcher/constants.py
repo_fetcher/exceptions.py
repo_fetcher/fetcher.py
repo_fetcher/models.py
repo_fetcher/utils.py
repo_fetcher/platforms/base.py
repo_fetcher/platforms/generic.py
repo_fetcher/platforms/github.py
repo_fetcher/platforms/gitlab.py
repo_fetcher-1.0.0.dist-info/licenses/LICENSE
repo_fetcher-1.0.0.dist-info/METADATA
repo_fetcher-1.0.0.dist-info/WHEEL
repo_fetcher-1.0.0.dist-info/top_level.txt
repo_fetcher-1.0.0.dist-info/RECORD
