Metadata-Version: 2.4
Name: repo-fetcher
Version: 1.0.0
Summary: Grab any repository, anywhere, anytime.
Requires-Python: >=3.12
License-File: LICENSE
Requires-Dist: aiohappyeyeballs==2.6.1
Requires-Dist: aiohttp==3.13.2
Requires-Dist: aiosignal==1.4.0
Requires-Dist: attrs==25.4.0
Requires-Dist: certifi==2025.11.12
Requires-Dist: charset-normalizer==3.4.4
Requires-Dist: click==8.3.1
Requires-Dist: frozenlist==1.8.0
Requires-Dist: idna==3.11
Requires-Dist: multidict==6.7.0
Requires-Dist: packaging==25.0
Requires-Dist: propcache==0.4.1
Requires-Dist: python-dotenv==1.2.1
Requires-Dist: requests==2.32.5
Requires-Dist: tqdm==4.67.1
Requires-Dist: typing-extensions==4.15.0
Requires-Dist: urllib3==2.6.2
Requires-Dist: yarl==1.22.0
Dynamic: license-file
